threeviz/__init__.py
threeviz/api.py
threeviz/core.py
threeviz/helpers.py
threeviz/test.py
threeviz-0.0.7.dist-info/METADATA
threeviz-0.0.7.dist-info/WHEEL
threeviz-0.0.7.dist-info/top_level.txt
threeviz-0.0.7.dist-info/RECORD
